{
	"alpha": "100",
	"special": {
		"background": "#fff2e7",
		"foreground": "#3a3a3a",
		"cursor": "#3a3a3a"
	},
	"colors": {
		"color0": "#fff2e7",
		"color1": "#f08080",
		"color2": "#f28c87",
		"color3": "#f4978e",
		"color4": "#f6a296",
		"color5": "#f8ad9d",
		"color6": "#fbc4ab",
		"color7": "#3a3a3a",
		"color8": "#fff2e7",
		"color9": "#f08080",
		"color10": "#f28c87",
		"color11": "#f4978e",
		"color12": "#f6a296",
		"color13": "#f8ad9d",
		"color14": "#fbc4ab",
		"color15": "#3a3a3a"
	}
}